uberping/__init__.py
uberping/cli.py
uberping/core.py
uberping/settings.py
uberping-0.0.1.1.dist-info/LICENSE
uberping-0.0.1.1.dist-info/METADATA
uberping-0.0.1.1.dist-info/WHEEL
uberping-0.0.1.1.dist-info/entry_points.txt
uberping-0.0.1.1.dist-info/top_level.txt
uberping-0.0.1.1.dist-info/RECORD
